Flask_Web3-0.1.1.dist-info/METADATA
Flask_Web3-0.1.1.dist-info/RECORD
Flask_Web3-0.1.1.dist-info/WHEEL
Flask_Web3-0.1.1.dist-info/top_level.txt
docs/__init__.py
docs/conf.py
flask_web3/__init__.py
flask_web3/config.py
flask_web3/extension.py
flask_web3/locals.py
flask_web3/utils.py
tests/__init__.py
tests/conftest.py
tests/test_extension.py
tests/test_import.py
tests/test_utils.py
