Metadata-Version: 2.1
Name: Flask-Web3
Version: 0.1.1
Summary: Flask extension allowing to smoothly integrate with web3.py.
Home-page: https://github.com/nmvalera/flask-web3
Author: Nicolas Maurice
Author-email: nicolas.maurice.valera@gmail.com
Maintainer: ConsenSys France
License: Copyright (c) 2017 by ConsenSys France and contributors.
